uart_module/uart_tx.v
// This file contains the UART Transmitter.  This transmitter is able
// to transmit 8 bits of serial data, one start bit, one stop bit,
// and no parity bit.  When transmit is complete o_Tx_done will be
// driven high for one clock cycle.
//
// Set Parameter CLKS_PER_BIT as follows:
// CLKS_PER_BIT = (Frequency of i_Clock)/(Frequency of UART)
// Example: 10 MHz Clock, 115200 baud UART
// (10000000)/(115200) = 87
  
module uart_tx 
  #(parameter CLKS_PER_BIT = 2)
  (
   input       i_Clock,
   input       i_Tx_DV,
   input [7:0] i_Tx_Byte, 
   output      o_Tx_Active,
   output reg  o_Tx_Serial,
   output      o_Tx_Done
   );
  
  parameter s_IDLE         = 3'b000;
  parameter s_TX_START_BIT = 3'b001;
  parameter s_TX_DATA_BITS = 3'b010;
  parameter s_TX_STOP_BIT  = 3'b011;
  parameter s_CLEANUP      = 3'b100;
   
  reg [2:0]    r_SM_Main     = 0;
  reg [7:0]    r_Clock_Count = 0;
  reg [2:0]    r_Bit_Index   = 0;
  reg [7:0]    r_Tx_Data     = 0;
  reg          r_Tx_Done     = 0;
  reg          r_Tx_Active   = 0;
     
  always @(posedge i_Clock)
    begin
       
      case (r_SM_Main)
        s_IDLE :
          begin
            o_Tx_Serial   <= 1'b1;         // Drive Line High for Idle
            r_Tx_Done     <= 1'b0;
            r_Clock_Count <= 0;
            r_Bit_Index   <= 0;
             
            if (i_Tx_DV == 1'b1)
              begin
                r_Tx_Active <= 1'b1;
                r_Tx_Data   <= i_Tx_Byte;
                r_SM_Main   <= s_TX_START_BIT;
              end
            else
              r_SM_Main <= s_IDLE;
          end // case: s_IDLE
         
         
        // Send out Start Bit. Start bit = 0
        s_TX_START_BIT :
          begin
            o_Tx_Serial <= 1'b0;
             
            // Wait CLKS_PER_BIT-1 clock cycles for start bit to finish
            if (r_Clock_Count < CLKS_PER_BIT-1)
              begin
                r_Clock_Count <= r_Clock_Count + 1;
                r_SM_Main     <= s_TX_START_BIT;
              end
            else
              begin
                r_Clock_Count <= 0;
                r_SM_Main     <= s_TX_DATA_BITS;
              end
          end // case: s_TX_START_BIT
         
         
        // Wait CLKS_PER_BIT-1 clock cycles for data bits to finish         
        s_TX_DATA_BITS :
          begin
            o_Tx_Serial <= r_Tx_Data[r_Bit_Index];
             
            if (r_Clock_Count < CLKS_PER_BIT-1)
              begin
                r_Clock_Count <= r_Clock_Count + 1;
                r_SM_Main     <= s_TX_DATA_BITS;
              end
            else
              begin
                r_Clock_Count <= 0;
                 
                // Check if we have sent out all bits
                if (r_Bit_Index < 7)
                  begin
                    r_Bit_Index <= r_Bit_Index + 1;
                    r_SM_Main   <= s_TX_DATA_BITS;
                  end
                else
                  begin
                    r_Bit_Index <= 0;
                    r_SM_Main   <= s_TX_STOP_BIT;
                  end
              end
          end // case: s_TX_DATA_BITS
         
         
        // Send out Stop bit.  Stop bit = 1
        s_TX_STOP_BIT :
          begin
            o_Tx_Serial <= 1'b1;
             
            // Wait CLKS_PER_BIT-1 clock cycles for Stop bit to finish
            if (r_Clock_Count < CLKS_PER_BIT-1)
              begin
                r_Clock_Count <= r_Clock_Count + 1;
                r_SM_Main     <= s_TX_STOP_BIT;
              end
            else
              begin
                r_Tx_Done     <= 1'b1;
                r_Clock_Count <= 0;
                r_SM_Main     <= s_CLEANUP;
                r_Tx_Active   <= 1'b0;
              end
          end // case: s_Tx_STOP_BIT
         
         
        // Stay here 1 clock
        s_CLEANUP :
          begin
            r_Tx_Done <= 1'b0;
            r_SM_Main <= s_IDLE;
          end
         
         
        default :
          r_SM_Main <= s_IDLE;
         
      endcase
    end
 
  assign o_Tx_Active = r_Tx_Active;
  assign o_Tx_Done   = r_Tx_Done;
   
endmodule

uart_module/uart_rx.v
// This file contains the UART Receiver.  This receiver is able to
// receive 8 bits of serial data, one start bit, one stop bit,
// and no parity bit.  When receive is complete o_rx_dv will be
// driven high for one clock cycle.
// 
// Set Parameter CLKS_PER_BIT as follows:
// CLKS_PER_BIT = (Frequency of i_Clock)/(Frequency of UART)
// Example: 10 MHz Clock, 115200 baud UART
// (10000000)/(115200) = 87
  
module uart_rx 
  #(parameter CLKS_PER_BIT = 87)
  (
   input        i_Clock,
   input        i_Rx_Serial,
   output       o_Rx_DV,
   output [7:0] o_Rx_Byte
   );
    
  parameter s_IDLE         = 3'b000;
  parameter s_RX_START_BIT = 3'b001;
  parameter s_RX_DATA_BITS = 3'b010;
  parameter s_RX_STOP_BIT  = 3'b011;
  parameter s_CLEANUP      = 3'b100;
   
  reg           r_Rx_Data_R = 1'b1;
  reg           r_Rx_Data   = 1'b1;
   
  reg [7:0]     r_Clock_Count = 0;
  reg [2:0]     r_Bit_Index   = 0; //8 bits total
  reg [7:0]     r_Rx_Byte     = 0;
  reg           r_Rx_DV       = 0;
  reg [2:0]     r_SM_Main     = 0;
   
  // Purpose: Double-register the incoming data.
  // This allows it to be used in the UART RX Clock Domain.
  // (It removes problems caused by metastability)
  always @(posedge i_Clock)
    begin
      r_Rx_Data_R <= i_Rx_Serial;
      r_Rx_Data   <= r_Rx_Data_R;
    end
   
   
  // Purpose: Control RX state machine
  always @(posedge i_Clock)
    begin
       
      case (r_SM_Main)
        s_IDLE :
          begin
            r_Rx_DV       <= 1'b0;
            r_Clock_Count <= 0;
            r_Bit_Index   <= 0;
             
            if (r_Rx_Data == 1'b0)          // Start bit detected
              r_SM_Main <= s_RX_START_BIT;
            else
              r_SM_Main <= s_IDLE;
          end
         
        // Check middle of start bit to make sure it's still low
        s_RX_START_BIT :
          begin
            if (r_Clock_Count == (CLKS_PER_BIT-1)/2)
              begin
                if (r_Rx_Data == 1'b0)
                  begin
                    r_Clock_Count <= 0;  // reset counter, found the middle
                    r_SM_Main     <= s_RX_DATA_BITS;
                  end
                else
                  r_SM_Main <= s_IDLE;
              end
            else
              begin
                r_Clock_Count <= r_Clock_Count + 1;
                r_SM_Main     <= s_RX_START_BIT;
              end
          end // case: s_RX_START_BIT
         
         
        // Wait CLKS_PER_BIT-1 clock cycles to sample serial data
        s_RX_DATA_BITS :
          begin
            if (r_Clock_Count < CLKS_PER_BIT-1)
              begin
                r_Clock_Count <= r_Clock_Count + 1;
                r_SM_Main     <= s_RX_DATA_BITS;
              end
            else
              begin
                r_Clock_Count          <= 0;
                r_Rx_Byte[r_Bit_Index] <= r_Rx_Data;
                 
                // Check if we have received all bits
                if (r_Bit_Index < 7)
                  begin
                    r_Bit_Index <= r_Bit_Index + 1;
                    r_SM_Main   <= s_RX_DATA_BITS;
                  end
                else
                  begin
                    r_Bit_Index <= 0;
                    r_SM_Main   <= s_RX_STOP_BIT;
                  end
              end
          end // case: s_RX_DATA_BITS
     
     
        // Receive Stop bit.  Stop bit = 1
        s_RX_STOP_BIT :
          begin
            // Wait CLKS_PER_BIT-1 clock cycles for Stop bit to finish
            if (r_Clock_Count < CLKS_PER_BIT-1)
              begin
                r_Clock_Count <= r_Clock_Count + 1;
                r_SM_Main     <= s_RX_STOP_BIT;
              end
            else
              begin
                r_Rx_DV       <= 1'b1;
                r_Clock_Count <= 0;
                r_SM_Main     <= s_CLEANUP;
              end
          end // case: s_RX_STOP_BIT
     
         
        // Stay here 1 clock
        s_CLEANUP :
          begin
            r_SM_Main <= s_IDLE;
            r_Rx_DV   <= 1'b0;
          end
         
         
        default :
          r_SM_Main <= s_IDLE;
         
      endcase
    end   
   
  assign o_Rx_DV   = r_Rx_DV;
  assign o_Rx_Byte = r_Rx_Byte;
   
endmodule // uart_rx

uart_module/uart_tb.v
//////////////////////////////////////////////////////////////////////
// File Downloaded from http://www.nandland.com
//////////////////////////////////////////////////////////////////////
 
// This testbench will exercise both the UART Tx and Rx.
// It sends out byte 0xAB over the transmitter
// It then exercises the receive by receiving byte 0x3F
`timescale 1ns/10ps
 
`include "uart_tx.v"
`include "uart_rx.v"
 
module uart_tb ();
 
  // Testbench uses a 10 MHz clock
  // Want to interface to 115200 baud UART
  // 10000000 / 115200 = 87 Clocks Per Bit.
  parameter c_CLOCK_PERIOD_NS = 100;
  parameter c_CLKS_PER_BIT    = 87;
  parameter c_BIT_PERIOD      = 8600;
   
  reg r_Clock = 0;
  reg r_Tx_DV = 0;
  wire w_Tx_Done;
  reg [7:0] r_Tx_Byte = 0;
  reg r_Rx_Serial = 1;
  wire [7:0] w_Rx_Byte;
   
initial 
  begin 
  $dumpfile("dump.vcd");
  $dumpvars;
end
  // Takes in input byte and serializes it 
  task UART_WRITE_BYTE;
    input [7:0] i_Data;
    integer     ii;
    begin
       
      // Send Start Bit
      r_Rx_Serial <= 1'b0;
      #(c_BIT_PERIOD);
      #1000;
       
       
      // Send Data Byte
      for (ii=0; ii<8; ii=ii+1)
        begin
          r_Rx_Serial <= i_Data[ii];
          #(c_BIT_PERIOD);
        end
       
      // Send Stop Bit
      r_Rx_Serial <= 1'b1;
      #(c_BIT_PERIOD);
     end
  endtask // UART_WRITE_BYTE
   
   
  uart_rx #(.CLKS_PER_BIT(c_CLKS_PER_BIT)) UART_RX_INST
    (.i_Clock(r_Clock),
     .i_Rx_Serial(r_Rx_Serial),
     .o_Rx_DV(),
     .o_Rx_Byte(w_Rx_Byte)
     );
   
  uart_tx #(.CLKS_PER_BIT(c_CLKS_PER_BIT)) UART_TX_INST
    (.i_Clock(r_Clock),
     .i_Tx_DV(r_Tx_DV),
     .i_Tx_Byte(r_Tx_Byte),
     .o_Tx_Active(),
     .o_Tx_Serial(),
     .o_Tx_Done(w_Tx_Done)
     );
 
   
  always
    #(c_CLOCK_PERIOD_NS/2) r_Clock <= !r_Clock;
 
   
  // Main Testing:
  initial
    begin
       
      // Tell UART to send a command (exercise Tx)
      @(posedge r_Clock);
      @(posedge r_Clock);
      r_Tx_DV <= 1'b1;
      r_Tx_Byte <= 8'hAB;
      @(posedge r_Clock);
      r_Tx_DV <= 1'b0;
      @(posedge w_Tx_Done);
       
      // Send a command to the UART (exercise Rx)
      @(posedge r_Clock);
      UART_WRITE_BYTE(8'h3F);
      @(posedge r_Clock);
             
      // Check that the correct command was received
      if (w_Rx_Byte == 8'h3F)
        $display("Test Passed - Correct Byte Received");
      else
        $display("Test Failed - Incorrect Byte Received");
      $finish;
       
    end
   
endmodule

uart_module/dump.vcd
$date
	Sun Aug 18 23:26:54 2024
$end
$version
	Icarus Verilog
$end
$timescale
	10ps
$end
$scope module uart_tb $end
$var wire 1 ! w_Tx_Done $end
$var wire 8 " w_Rx_Byte [7:0] $end
$var parameter 32 # c_BIT_PERIOD $end
$var parameter 32 $ c_CLKS_PER_BIT $end
$var parameter 32 % c_CLOCK_PERIOD_NS $end
$var reg 1 & r_Clock $end
$var reg 1 ' r_Rx_Serial $end
$var reg 8 ( r_Tx_Byte [7:0] $end
$var reg 1 ) r_Tx_DV $end
$scope module UART_RX_INST $end
$var wire 1 & i_Clock $end
$var wire 1 ' i_Rx_Serial $end
$var wire 8 * o_Rx_Byte [7:0] $end
$var wire 1 + o_Rx_DV $end
$var parameter 32 , CLKS_PER_BIT $end
$var parameter 3 - s_CLEANUP $end
$var parameter 3 . s_IDLE $end
$var parameter 3 / s_RX_DATA_BITS $end
$var parameter 3 0 s_RX_START_BIT $end
$var parameter 3 1 s_RX_STOP_BIT $end
$var reg 3 2 r_Bit_Index [2:0] $end
$var reg 8 3 r_Clock_Count [7:0] $end
$var reg 8 4 r_Rx_Byte [7:0] $end
$var reg 1 5 r_Rx_DV $end
$var reg 1 6 r_Rx_Data $end
$var reg 1 7 r_Rx_Data_R $end
$var reg 3 8 r_SM_Main [2:0] $end
$upscope $end
$scope module UART_TX_INST $end
$var wire 1 & i_Clock $end
$var wire 8 9 i_Tx_Byte [7:0] $end
$var wire 1 ) i_Tx_DV $end
$var wire 1 : o_Tx_Active $end
$var wire 1 ! o_Tx_Done $end
$var parameter 32 ; CLKS_PER_BIT $end
$var parameter 3 < s_CLEANUP $end
$var parameter 3 = s_IDLE $end
$var parameter 3 > s_TX_DATA_BITS $end
$var parameter 3 ? s_TX_START_BIT $end
$var parameter 3 @ s_TX_STOP_BIT $end
$var reg 1 A o_Tx_Serial $end
$var reg 3 B r_Bit_Index [2:0] $end
$var reg 8 C r_Clock_Count [7:0] $end
$var reg 3 D r_SM_Main [2:0] $end
$var reg 1 E r_Tx_Active $end
$var reg 8 F r_Tx_Data [7:0] $end
$var reg 1 G r_Tx_Done $end
$upscope $end
$scope task UART_WRITE_BYTE $end
$var reg 8 H i_Data [7:0] $end
$var integer 32 I ii [31:0] $end
$upscope $end
$upscope $end
$enddefinitions $end
$comment Show the parameter values. $end
$dumpall
b11 @
b1 ?
b10 >
b0 =
b100 <
b1010111 ;
b11 1
b1 0
b10 /
b0 .
b100 -
b1010111 ,
b1100100 %
b1010111 $
b10000110011000 #
$end
#0
$dumpvars
bx I
bx H
0G
b0 F
0E
b0 D
b0 C
b0 B
xA
0:
b0 9
b0 8
17
16
05
b0 4
b0 3
b0 2
0+
b0 *
0)
b0 (
1'
0&
b0 "
0!
$end
#5000
1A
1&
#10000
0&
#15000
b10101011 (
b10101011 9
1)
1&
#20000
0&
#25000
b1 D
b10101011 F
1:
1E
0)
1&
#30000
0&
#35000
b1 C
0A
1&
#40000
0&
#45000
b10 C
1&
#50000
0&
#55000
b11 C
1&
#60000
0&
#65000
b100 C
1&
#70000
0&
#75000
b101 C
1&
#80000
0&
#85000
b110 C
1&
#90000
0&
#95000
b111 C
1&
#100000
0&
#105000
b1000 C
1&
#110000
0&
#115000
b1001 C
1&
#120000
0&
#125000
b1010 C
1&
#130000
0&
#135000
b1011 C
1&
#140000
0&
#145000
b1100 C
1&
#150000
0&
#155000
b1101 C
1&
#160000
0&
#165000
b1110 C
1&
#170000
0&
#175000
b1111 C
1&
#180000
0&
#185000
b10000 C
1&
#190000
0&
#195000
b10001 C
1&
#200000
0&
#205000
b10010 C
1&
#210000
0&
#215000
b10011 C
1&
#220000
0&
#225000
b10100 C
1&
#230000
0&
#235000
b10101 C
1&
#240000
0&
#245000
b10110 C
1&
#250000
0&
#255000
b10111 C
1&
#260000
0&
#265000
b11000 C
1&
#270000
0&
#275000
b11001 C
1&
#280000
0&
#285000
b11010 C
1&
#290000
0&
#295000
b11011 C
1&
#300000
0&
#305000
b11100 C
1&
#310000
0&
#315000
b11101 C
1&
#320000
0&
#325000
b11110 C
1&
#330000
0&
#335000
b11111 C
1&
#340000
0&
#345000
b100000 C
1&
#350000
0&
#355000
b100001 C
1&
#360000
0&
#365000
b100010 C
1&
#370000
0&
#375000
b100011 C
1&
#380000
0&
#385000
b100100 C
1&
#390000
0&
#395000
b100101 C
1&
#400000
0&
#405000
b100110 C
1&
#410000
0&
#415000
b100111 C
1&
#420000
0&
#425000
b101000 C
1&
#430000
0&
#435000
b101001 C
1&
#440000
0&
#445000
b101010 C
1&
#450000
0&
#455000
b101011 C
1&
#460000
0&
#465000
b101100 C
1&
#470000
0&
#475000
b101101 C
1&
#480000
0&
#485000
b101110 C
1&
#490000
0&
#495000
b101111 C
1&
#500000
0&
#505000
b110000 C
1&
#510000
0&
#515000
b110001 C
1&
#520000
0&
#525000
b110010 C
1&
#530000
0&
#535000
b110011 C
1&
#540000
0&
#545000
b110100 C
1&
#550000
0&
#555000
b110101 C
1&
#560000
0&
#565000
b110110 C
1&
#570000
0&
#575000
b110111 C
1&
#580000
0&
#585000
b111000 C
1&
#590000
0&
#595000
b111001 C
1&
#600000
0&
#605000
b111010 C
1&
#610000
0&
#615000
b111011 C
1&
#620000
0&
#625000
b111100 C
1&
#630000
0&
#635000
b111101 C
1&
#640000
0&
#645000
b111110 C
1&
#650000
0&
#655000
b111111 C
1&
#660000
0&
#665000
b1000000 C
1&
#670000
0&
#675000
b1000001 C
1&
#680000
0&
#685000
b1000010 C
1&
#690000
0&
#695000
b1000011 C
1&
#700000
0&
#705000
b1000100 C
1&
#710000
0&
#715000
b1000101 C
1&
#720000
0&
#725000
b1000110 C
1&
#730000
0&
#735000
b1000111 C
1&
#740000
0&
#745000
b1001000 C
1&
#750000
0&
#755000
b1001001 C
1&
#760000
0&
#765000
b1001010 C
1&
#770000
0&
#775000
b1001011 C
1&
#780000
0&
#785000
b1001100 C
1&
#790000
0&
#795000
b1001101 C
1&
#800000
0&
#805000
b1001110 C
1&
#810000
0&
#815000
b1001111 C
1&
#820000
0&
#825000
b1010000 C
1&
#830000
0&
#835000
b1010001 C
1&
#840000
0&
#845000
b1010010 C
1&
#850000
0&
#855000
b1010011 C
1&
#860000
0&
#865000
b1010100 C
1&
#870000
0&
#875000
b1010101 C
1&
#880000
0&
#885000
b1010110 C
1&
#890000
0&
#895000
b10 D
b0 C
1&
#900000
0&
#905000
b1 C
1A
1&
#910000
0&
#915000
b10 C
1&
#920000
0&
#925000
b11 C
1&
#930000
0&
#935000
b100 C
1&
#940000
0&
#945000
b101 C
1&
#950000
0&
#955000
b110 C
1&
#960000
0&
#965000
b111 C
1&
#970000
0&
#975000
b1000 C
1&
#980000
0&
#985000
b1001 C
1&
#990000
0&
#995000
b1010 C
1&
#1000000
0&
#1005000
b1011 C
1&
#1010000
0&
#1015000
b1100 C
1&
#1020000
0&
#1025000
b1101 C
1&
#1030000
0&
#1035000
b1110 C
1&
#1040000
0&
#1045000
b1111 C
1&
#1050000
0&
#1055000
b10000 C
1&
#1060000
0&
#1065000
b10001 C
1&
#1070000
0&
#1075000
b10010 C
1&
#1080000
0&
#1085000
b10011 C
1&
#1090000
0&
#1095000
b10100 C
1&
#1100000
0&
#1105000
b10101 C
1&
#1110000
0&
#1115000
b10110 C
1&
#1120000
0&
#1125000
b10111 C
1&
#1130000
0&
#1135000
b11000 C
1&
#1140000
0&
#1145000
b11001 C
1&
#1150000
0&
#1155000
b11010 C
1&
#1160000
0&
#1165000
b11011 C
1&
#1170000
0&
#1175000
b11100 C
1&
#1180000
0&
#1185000
b11101 C
1&
#1190000
0&
#1195000
b11110 C
1&
#1200000
0&
#1205000
b11111 C
1&
#1210000
0&
#1215000
b100000 C
1&
#1220000
0&
#1225000
b100001 C
1&
#1230000
0&
#1235000
b100010 C
1&
#1240000
0&
#1245000
b100011 C
1&
#1250000
0&
#1255000
b100100 C
1&
#1260000
0&
#1265000
b100101 C
1&
#1270000
0&
#1275000
b100110 C
1&
#1280000
0&
#1285000
b100111 C
1&
#1290000
0&
#1295000
b101000 C
1&
#1300000
0&
#1305000
b101001 C
1&
#1310000
0&
#1315000
b101010 C
1&
#1320000
0&
#1325000
b101011 C
1&
#1330000
0&
#1335000
b101100 C
1&
#1340000
0&
#1345000
b101101 C
1&
#1350000
0&
#1355000
b101110 C
1&
#1360000
0&
#1365000
b101111 C
1&
#1370000
0&
#1375000
b110000 C
1&
#1380000
0&
#1385000
b110001 C
1&
#1390000
0&
#1395000
b110010 C
1&
#1400000
0&
#1405000
b110011 C
1&
#1410000
0&
#1415000
b110100 C
1&
#1420000
0&
#1425000
b110101 C
1&
#1430000
0&
#1435000
b110110 C
1&
#1440000
0&
#1445000
b110111 C
1&
#1450000
0&
#1455000
b111000 C
1&
#1460000
0&
#1465000
b111001 C
1&
#1470000
0&
#1475000
b111010 C
1&
#1480000
0&
#1485000
b111011 C
1&
#1490000
0&
#1495000
b111100 C
1&
#1500000
0&
#1505000
b111101 C
1&
#1510000
0&
#1515000
b111110 C
1&
#1520000
0&
#1525000
b111111 C
1&
#1530000
0&
#1535000
b1000000 C
1&
#1540000
0&
#1545000
b1000001 C
1&
#1550000
0&
#1555000
b1000010 C
1&
#1560000
0&
#1565000
b1000011 C
1&
#1570000
0&
#1575000
b1000100 C
1&
#1580000
0&
#1585000
b1000101 C
1&
#1590000
0&
#1595000
b1000110 C
1&
#1600000
0&
#1605000
b1000111 C
1&
#1610000
0&
#1615000
b1001000 C
1&
#1620000
0&
#1625000
b1001001 C
1&
#1630000
0&
#1635000
b1001010 C
1&
#1640000
0&
#1645000
b1001011 C
1&
#1650000
0&
#1655000
b1001100 C
1&
#1660000
0&
#1665000
b1001101 C
1&
#1670000
0&
#1675000
b1001110 C
1&
#1680000
0&
#1685000
b1001111 C
1&
#1690000
0&
#1695000
b1010000 C
1&
#1700000
0&
#1705000
b1010001 C
1&
#1710000
0&
#1715000
b1010010 C
1&
#1720000
0&
#1725000
b1010011 C
1&
#1730000
0&
#1735000
b1010100 C
1&
#1740000
0&
#1745000
b1010101 C
1&
#1750000
0&
#1755000
b1010110 C
1&
#1760000
0&
#1765000
b1 B
b0 C
1&
#1770000
0&
#1775000
b1 C
1&
#1780000
0&
#1785000
b10 C
1&
#1790000
0&
#1795000
b11 C
1&
#1800000
0&
#1805000
b100 C
1&
#1810000
0&
#1815000
b101 C
1&
#1820000
0&
#1825000
b110 C
1&
#1830000
0&
#1835000
b111 C
1&
#1840000
0&
#1845000
b1000 C
1&
#1850000
0&
#1855000
b1001 C
1&
#1860000
0&
#1865000
b1010 C
1&
#1870000
0&
#1875000
b1011 C
1&
#1880000
0&
#1885000
b1100 C
1&
#1890000
0&
#1895000
b1101 C
1&
#1900000
0&
#1905000
b1110 C
1&
#1910000
0&
#1915000
b1111 C
1&
#1920000
0&
#1925000
b10000 C
1&
#1930000
0&
#1935000
b10001 C
1&
#1940000
0&
#1945000
b10010 C
1&
#1950000
0&
#1955000
b10011 C
1&
#1960000
0&
#1965000
b10100 C
1&
#1970000
0&
#1975000
b10101 C
1&
#1980000
0&
#1985000
b10110 C
1&
#1990000
0&
#1995000
b10111 C
1&
#2000000
0&
#2005000
b11000 C
1&
#2010000
0&
#2015000
b11001 C
1&
#2020000
0&
#2025000
b11010 C
1&
#2030000
0&
#2035000
b11011 C
1&
#2040000
0&
#2045000
b11100 C
1&
#2050000
0&
#2055000
b11101 C
1&
#2060000
0&
#2065000
b11110 C
1&
#2070000
0&
#2075000
b11111 C
1&
#2080000
0&
#2085000
b100000 C
1&
#2090000
0&
#2095000
b100001 C
1&
#2100000
0&
#2105000
b100010 C
1&
#2110000
0&
#2115000
b100011 C
1&
#2120000
0&
#2125000
b100100 C
1&
#2130000
0&
#2135000
b100101 C
1&
#2140000
0&
#2145000
b100110 C
1&
#2150000
0&
#2155000
b100111 C
1&
#2160000
0&
#2165000
b101000 C
1&
#2170000
0&
#2175000
b101001 C
1&
#2180000
0&
#2185000
b101010 C
1&
#2190000
0&
#2195000
b101011 C
1&
#2200000
0&
#2205000
b101100 C
1&
#2210000
0&
#2215000
b101101 C
1&
#2220000
0&
#2225000
b101110 C
1&
#2230000
0&
#2235000
b101111 C
1&
#2240000
0&
#2245000
b110000 C
1&
#2250000
0&
#2255000
b110001 C
1&
#2260000
0&
#2265000
b110010 C
1&
#2270000
0&
#2275000
b110011 C
1&
#2280000
0&
#2285000
b110100 C
1&
#2290000
0&
#2295000
b110101 C
1&
#2300000
0&
#2305000
b110110 C
1&
#2310000
0&
#2315000
b110111 C
1&
#2320000
0&
#2325000
b111000 C
1&
#2330000
0&
#2335000
b111001 C
1&
#2340000
0&
#2345000
b111010 C
1&
#2350000
0&
#2355000
b111011 C
1&
#2360000
0&
#2365000
b111100 C
1&
#2370000
0&
#2375000
b111101 C
1&
#2380000
0&
#2385000
b111110 C
1&
#2390000
0&
#2395000
b111111 C
1&
#2400000
0&
#2405000
b1000000 C
1&
#2410000
0&
#2415000
b1000001 C
1&
#2420000
0&
#2425000
b1000010 C
1&
#2430000
0&
#2435000
b1000011 C
1&
#2440000
0&
#2445000
b1000100 C
1&
#2450000
0&
#2455000
b1000101 C
1&
#2460000
0&
#2465000
b1000110 C
1&
#2470000
0&
#2475000
b1000111 C
1&
#2480000
0&
#2485000
b1001000 C
1&
#2490000
0&
#2495000
b1001001 C
1&
#2500000
0&
#2505000
b1001010 C
1&
#2510000
0&
#2515000
b1001011 C
1&
#2520000
0&
#2525000
b1001100 C
1&
#2530000
0&
#2535000
b1001101 C
1&
#2540000
0&
#2545000
b1001110 C
1&
#2550000
0&
#2555000
b1001111 C
1&
#2560000
0&
#2565000
b1010000 C
1&
#2570000
0&
#2575000
b1010001 C
1&
#2580000
0&
#2585000
b1010010 C
1&
#2590000
0&
#2595000
b1010011 C
1&
#2600000
0&
#2605000
b1010100 C
1&
#2610000
0&
#2615000
b1010101 C
1&
#2620000
0&
#2625000
b1010110 C
1&
#2630000
0&
#2635000
b10 B
b0 C
1&
#2640000
0&
#2645000
b1 C
0A
1&
#2650000
0&
#2655000
b10 C
1&
#2660000
0&
#2665000
b11 C
1&
#2670000
0&
#2675000
b100 C
1&
#2680000
0&
#2685000
b101 C
1&
#2690000
0&
#2695000
b110 C
1&
#2700000
0&
#2705000
b111 C
1&
#2710000
0&
#2715000
b1000 C
1&
#2720000
0&
#2725000
b1001 C
1&
#2730000
0&
#2735000
b1010 C
1&
#2740000
0&
#2745000
b1011 C
1&
#2750000
0&
#2755000
b1100 C
1&
#2760000
0&
#2765000
b1101 C
1&
#2770000
0&
#2775000
b1110 C
1&
#2780000
0&
#2785000
b1111 C
1&
#2790000
0&
#2795000
b10000 C
1&
#2800000
0&
#2805000
b10001 C
1&
#2810000
0&
#2815000
b10010 C
1&
#2820000
0&
#2825000
b10011 C
1&
#2830000
0&
#2835000
b10100 C
1&
#2840000
0&
#2845000
b10101 C
1&
#2850000
0&
#2855000
b10110 C
1&
#2860000
0&
#2865000
b10111 C
1&
#2870000
0&
#2875000
b11000 C
1&
#2880000
0&
#2885000
b11001 C
1&
#2890000
0&
#2895000
b11010 C
1&
#2900000
0&
#2905000
b11011 C
1&
#2910000
0&
#2915000
b11100 C
1&
#2920000
0&
#2925000
b11101 C
1&
#2930000
0&
#2935000
b11110 C
1&
#2940000
0&
#2945000
b11111 C
1&
#2950000
0&
#2955000
b100000 C
1&
#2960000
0&
#2965000
b100001 C
1&
#2970000
0&
#2975000
b100010 C
1&
#2980000
0&
#2985000
b100011 C
1&
#2990000
0&
#2995000
b100100 C
1&
#3000000
0&
#3005000
b100101 C
1&
#3010000
0&
#3015000
b100110 C
1&
#3020000
0&
#3025000
b100111 C
1&
#3030000
0&
#3035000
b101000 C
1&
#3040000
0&
#3045000
b101001 C
1&
#3050000
0&
#3055000
b101010 C
1&
#3060000
0&
#3065000
b101011 C
1&
#3070000
0&
#3075000
b101100 C
1&
#3080000
0&
#3085000
b101101 C
1&
#3090000
0&
#3095000
b101110 C
1&
#3100000
0&
#3105000
b101111 C
1&
#3110000
0&
#3115000
b110000 C
1&
#3120000
0&
#3125000
b110001 C
1&
#3130000
0&
#3135000
b110010 C
1&
#3140000
0&
#3145000
b110011 C
1&
#3150000
0&
#3155000
b110100 C
1&
#3160000
0&
#3165000
b110101 C
1&
#3170000
0&
#3175000
b110110 C
1&
#3180000
0&
#3185000
b110111 C
1&
#3190000
0&
#3195000
b111000 C
1&
#3200000
0&
#3205000
b111001 C
1&
#3210000
0&
#3215000
b111010 C
1&
#3220000
0&
#3225000
b111011 C
1&
#3230000
0&
#3235000
b111100 C
1&
#3240000
0&
#3245000
b111101 C
1&
#3250000
0&
#3255000
b111110 C
1&
#3260000
0&
#3265000
b111111 C
1&
#3270000
0&
#3275000
b1000000 C
1&
#3280000
0&
#3285000
b1000001 C
1&
#3290000
0&
#3295000
b1000010 C
1&
#3300000
0&
#3305000
b1000011 C
1&
#3310000
0&
#3315000
b1000100 C
1&
#3320000
0&
#3325000
b1000101 C
1&
#3330000
0&
#3335000
b1000110 C
1&
#3340000
0&
#3345000
b1000111 C
1&
#3350000
0&
#3355000
b1001000 C
1&
#3360000
0&
#3365000
b1001001 C
1&
#3370000
0&
#3375000
b1001010 C
1&
#3380000
0&
#3385000
b1001011 C
1&
#3390000
0&
#3395000
b1001100 C
1&
#3400000
0&
#3405000
b1001101 C
1&
#3410000
0&
#3415000
b1001110 C
1&
#3420000
0&
#3425000
b1001111 C
1&
#3430000
0&
#3435000
b1010000 C
1&
#3440000
0&
#3445000
b1010001 C
1&
#3450000
0&
#3455000
b1010010 C
1&
#3460000
0&
#3465000
b1010011 C
1&
#3470000
0&
#3475000
b1010100 C
1&
#3480000
0&
#3485000
b1010101 C
1&
#3490000
0&
#3495000
b1010110 C
1&
#3500000
0&
#3505000
b11 B
b0 C
1&
#3510000
0&
#3515000
b1 C
1A
1&
#3520000
0&
#3525000
b10 C
1&
#3530000
0&
#3535000
b11 C
1&
#3540000
0&
#3545000
b100 C
1&
#3550000
0&
#3555000
b101 C
1&
#3560000
0&
#3565000
b110 C
1&
#3570000
0&
#3575000
b111 C
1&
#3580000
0&
#3585000
b1000 C
1&
#3590000
0&
#3595000
b1001 C
1&
#3600000
0&
#3605000
b1010 C
1&
#3610000
0&
#3615000
b1011 C
1&
#3620000
0&
#3625000
b1100 C
1&
#3630000
0&
#3635000
b1101 C
1&
#3640000
0&
#3645000
b1110 C
1&
#3650000
0&
#3655000
b1111 C
1&
#3660000
0&
#3665000
b10000 C
1&
#3670000
0&
#3675000
b10001 C
1&
#3680000
0&
#3685000
b10010 C
1&
#3690000
0&
#3695000
b10011 C
1&
#3700000
0&
#3705000
b10100 C
1&
#3710000
0&
#3715000
b10101 C
1&
#3720000
0&
#3725000
b10110 C
1&
#3730000
0&
#3735000
b10111 C
1&
#3740000
0&
#3745000
b11000 C
1&
#3750000
0&
#3755000
b11001 C
1&
#3760000
0&
#3765000
b11010 C
1&
#3770000
0&
#3775000
b11011 C
1&
#3780000
0&
#3785000
b11100 C
1&
#3790000
0&
#3795000
b11101 C
1&
#3800000
0&
#3805000
b11110 C
1&
#3810000
0&
#3815000
b11111 C
1&
#3820000
0&
#3825000
b100000 C
1&
#3830000
0&
#3835000
b100001 C
1&
#3840000
0&
#3845000
b100010 C
1&
#3850000
0&
#3855000
b100011 C
1&
#3860000
0&
#3865000
b100100 C
1&
#3870000
0&
#3875000
b100101 C
1&
#3880000
0&
#3885000
b100110 C
1&
